{
    "1": {
        "instId": 1,
        "charId": "char_002_amiya",
        "favorPoint": 0,
        "potentialRank": 0,
        "mainSkillLvl": 1,
        "skin": "char_002_amiya#1",
        "level": 1,
        "exp": 0,
        "evolvePhase": 0,
        "defaultSkillIndex": 0,
        "gainTime": 0,
        "skills": [
            {
                "skillId": "skcom_magic_rage[3]",
                "unlock": 1,
                "state": 0,
                "specializeLevel": 0,
                "completeUpgradeTime": -1
            },
            {
                "skillId": "skchr_amiya_2",
                "unlock": 0,
                "state": 0,
                "specializeLevel": 0,
                "completeUpgradeTime": -1
            },
            {
                "skillId": "skchr_amiya_3",
                "unlock": 0,
                "state": 0,
                "specializeLevel": 0,
                "completeUpgradeTime": -1
            }
        ]
    },
    "2": {
        "instId": 2,
        "charId": "char_502_nblade",
        "favorPoint": 0,
        "potentialRank": 0,
        "mainSkillLvl": 1,
        "skin": "char_502_nblade#1",
        "level": 1,
        "exp": 0,
        "evolvePhase": 0,
        "defaultSkillIndex": -1,
        "gainTime": 0,
        "skills": [

        ]
    },
    "3": {
        "instId": 3,
        "charId": "char_500_noirc",
        "favorPoint": 0,
        "potentialRank": 0,
        "mainSkillLvl": 1,
        "skin": "char_500_noirc#1",
        "level": 1,
        "exp": 0,
        "evolvePhase": 0,
        "defaultSkillIndex": -1,
        "gainTime": 0,
        "skills": [

        ]
    },
    "4": {
        "instId": 4,
        "charId": "char_503_rang",
        "favorPoint": 0,
        "potentialRank": 0,
        "mainSkillLvl": 1,
        "skin": "char_503_rang#1",
        "level": 1,
        "exp": 0,
        "evolvePhase": 0,
        "defaultSkillIndex": -1,
        "gainTime": 0,
        "skills": [

        ]
    }
}